monogress/__init__.py
monogress-0.1.0.dist-info/METADATA
monogress-0.1.0.dist-info/WHEEL
monogress-0.1.0.dist-info/top_level.txt
monogress-0.1.0.dist-info/RECORD
