Metadata-Version: 2.1
Name: monogress
Version: 0.1.0
Summary: Monotonic univariate regression
Home-page: UNKNOWN
Author: Francis B. Lavoie
Author-email: francis.b.lavoie@usherbrooke.ca
License: UNKNOWN
Platform: UNKNOWN
Classifier: Programming Language :: Python :: 3
Classifier: License :: OSI Approved :: BSD License
Classifier: Operating System :: OS Independent
Requires-Dist: scipy
